LICENSE
MANIFEST.in
README.md
requirements.txt
setup.cfg
setup.py
poseidonctrip/VERSION
poseidonctrip/__init__.py
poseidonctrip.egg-info/PKG-INFO
poseidonctrip.egg-info/SOURCES.txt
poseidonctrip.egg-info/dependency_links.txt
poseidonctrip.egg-info/entry_points.txt
poseidonctrip.egg-info/requires.txt
poseidonctrip.egg-info/top_level.txt
poseidonctrip/cmd/__init__.py
poseidonctrip/cmd/init.py
poseidonctrip/cmd/server.py
poseidonctrip/downloadermiddlewares/__init__.py
poseidonctrip/downloadermiddlewares/cookies.py
poseidonctrip/downloadermiddlewares/proxy.py
poseidonctrip/pipelines/__init__.py
poseidonctrip/pipelines/mongo.py
poseidonctrip/pipelines/mysql.py
poseidonctrip/server/__init__.py
poseidonctrip/server/manage.py
poseidonctrip/server/core/__init__.py
poseidonctrip/server/core/admin.py
poseidonctrip/server/core/apps.py
poseidonctrip/server/core/build.py
poseidonctrip/server/core/config.py
poseidonctrip/server/core/encoder.py
poseidonctrip/server/core/middlewares.py
poseidonctrip/server/core/models.py
poseidonctrip/server/core/response.py
poseidonctrip/server/core/tests.py
poseidonctrip/server/core/time.py
poseidonctrip/server/core/urls.py
poseidonctrip/server/core/utils.py
poseidonctrip/server/core/views.py
poseidonctrip/server/core/templates/favicon.ico
poseidonctrip/server/core/templates/index.html
poseidonctrip/server/core/templates/static/css/631f3db5.css
poseidonctrip/server/core/templates/static/css/b057a267.css
poseidonctrip/server/core/templates/static/fonts/674f50d2.eot
poseidonctrip/server/core/templates/static/fonts/af7ae505.woff2
poseidonctrip/server/core/templates/static/fonts/b02bdc1b.ttf
poseidonctrip/server/core/templates/static/fonts/b06871f2.ttf
poseidonctrip/server/core/templates/static/fonts/d2f69a92.woff
poseidonctrip/server/core/templates/static/fonts/fee66e71.woff
poseidonctrip/server/core/templates/static/images/0aa9679a.png
poseidonctrip/server/core/templates/static/images/1ac624ba.png
poseidonctrip/server/core/templates/static/images/864753ef.svg
poseidonctrip/server/core/templates/static/images/912ec66d.svg
poseidonctrip/server/core/templates/static/images/a551c521.png
poseidonctrip/server/core/templates/static/js/314e2244.js
