Metadata-Version: 1.0
Name: poseidonctrip
Version: 0.9.1
Summary: distributed crawler
Home-page: http://pypi.python.org/pypi/poseidonctrip/
Author: hantmac
Author-email: hantmac@outlook.com
License: MIT
Keywords: poseidonctrip,scrapy,distributed
Platform: UNKNOWN
